qlty/__init__.py
qlty/backends_2_5D.py
qlty/base.py
qlty/cleanup.py
qlty/patch_pairs_2d.py
qlty/patch_pairs_3d.py
qlty/qlty2D.py
qlty/qlty2DLarge.py
qlty/qlty2_5D.py
qlty/qlty3D.py
qlty/qlty3DLarge.py
qlty/pretokenizer_2d/__init__.py
qlty/pretokenizer_2d/sequences.py
qlty/utils/__init__.py
qlty/utils/false_color_2D.py
qlty/utils/stack_to_zarr.py
qlty-1.5.0.dist-info/licenses/AUTHORS.rst
qlty-1.5.0.dist-info/licenses/LICENSE
qlty-1.5.0.dist-info/METADATA
qlty-1.5.0.dist-info/WHEEL
qlty-1.5.0.dist-info/top_level.txt
qlty-1.5.0.dist-info/RECORD
