Metadata-Version: 2.4
Name: qlty
Version: 1.5.0
Summary: Unstitch and stitch back pytorch tensors
Author-email: "Petrus H. Zwart" <PHZwart@lbl.gov>
License: BSD
Project-URL: Homepage, https://github.com/phzwart/qlty
Project-URL: Documentation, https://qlty.readthedocs.io/
Project-URL: Repository, https://github.com/phzwart/qlty
Project-URL: Issues, https://github.com/phzwart/qlty/issues
Keywords: qlty,pytorch,tensor,stitch,unstitch,patch,image
Classifier: Development Status :: 4 - Beta
Classifier: Intended Audience :: Developers
Classifier: Intended Audience :: Science/Research
Classifier: License :: OSI Approved :: BSD License
Classifier: Natural Language :: English
Classifier: Programming Language :: Python :: 3
Classifier: Programming Language :: Python :: 3.8
Classifier: Programming Language :: Python :: 3.9
Classifier: Programming Language :: Python :: 3.10
Classifier: Programming Language :: Python :: 3.11
Classifier: Topic :: Scientific/Engineering
Classifier: Topic :: Software Development :: Libraries :: Python Modules
Requires-Python: >=3.8
License-File: LICENSE
License-File: AUTHORS.rst
Requires-Dist: numpy>=1.20.1
Requires-Dist: torch>=1.11
Requires-Dist: einops>=0.3.0
Requires-Dist: scipy>=1.8.1
Requires-Dist: zarr>=3.0.0a5
Requires-Dist: numba>=0.56.0
Requires-Dist: dask>=2021.12.0
Requires-Dist: umap-learn>=0.5.0
Requires-Dist: scikit-learn>=1.0.0
Provides-Extra: docs
Requires-Dist: sphinx; extra == "docs"
Requires-Dist: sphinx_rtd_theme; extra == "docs"
Provides-Extra: tests
Requires-Dist: pytest>=8.0.0; extra == "tests"
Requires-Dist: coverage>=7.0.0; extra == "tests"
Requires-Dist: tifffile>=2021.0.0; extra == "tests"
Dynamic: description
Dynamic: description-content-type
Dynamic: license-file
